SAMYOL/__init__.py
SAMYOL/prediction_results.py
SAMYOL/predictor.py
SAMYOL/sam_inference.py
SAMYOL/utils.py
SAMYOL/yolo_inference.py
SAMYOL/yolo_postprocessing.py
SAMYOL/yolo_preprocessing.py
SAMYOL-1.0.9.dist-info/LICENSE
SAMYOL-1.0.9.dist-info/METADATA
SAMYOL-1.0.9.dist-info/WHEEL
SAMYOL-1.0.9.dist-info/top_level.txt
SAMYOL-1.0.9.dist-info/RECORD
